SoftLayer/API.py
SoftLayer/__init__.py
SoftLayer/auth.py
SoftLayer/config.py
SoftLayer/consts.py
SoftLayer/decoration.py
SoftLayer/exceptions.py
SoftLayer/utils.py
SoftLayer/CLI/__init__.py
SoftLayer/CLI/call_api.py
SoftLayer/CLI/columns.py
SoftLayer/CLI/command.py
SoftLayer/CLI/core.py
SoftLayer/CLI/custom_types.py
SoftLayer/CLI/environment.py
SoftLayer/CLI/exceptions.py
SoftLayer/CLI/formatting.py
SoftLayer/CLI/helpers.py
SoftLayer/CLI/login.py
SoftLayer/CLI/metadata.py
SoftLayer/CLI/routes.py
SoftLayer/CLI/search.py
SoftLayer/CLI/storage_utils.py
SoftLayer/CLI/summary.py
SoftLayer/CLI/template.py
SoftLayer/CLI/account/__init__.py
SoftLayer/CLI/account/billing_items.py
SoftLayer/CLI/account/cancel_item.py
SoftLayer/CLI/account/event_detail.py
SoftLayer/CLI/account/events.py
SoftLayer/CLI/account/hook_create.py
SoftLayer/CLI/account/hook_delete.py
SoftLayer/CLI/account/hooks.py
SoftLayer/CLI/account/invoice_detail.py
SoftLayer/CLI/account/invoices.py
SoftLayer/CLI/account/item_detail.py
SoftLayer/CLI/account/licenses.py
SoftLayer/CLI/account/orders.py
SoftLayer/CLI/account/summary.py
SoftLayer/CLI/bandwidth/__init__.py
SoftLayer/CLI/bandwidth/pools.py
SoftLayer/CLI/bandwidth/pools_create.py
SoftLayer/CLI/bandwidth/pools_delete.py
SoftLayer/CLI/bandwidth/pools_detail.py
SoftLayer/CLI/bandwidth/pools_edit.py
SoftLayer/CLI/bandwidth/summary.py
SoftLayer/CLI/block/__init__.py
SoftLayer/CLI/block/cancel.py
SoftLayer/CLI/block/convert.py
SoftLayer/CLI/block/count.py
SoftLayer/CLI/block/detail.py
SoftLayer/CLI/block/duplicate.py
SoftLayer/CLI/block/duplicate_convert_status.py
SoftLayer/CLI/block/limit.py
SoftLayer/CLI/block/list.py
SoftLayer/CLI/block/lun.py
SoftLayer/CLI/block/modify.py
SoftLayer/CLI/block/object_list.py
SoftLayer/CLI/block/object_storage_detail.py
SoftLayer/CLI/block/object_storage_permission.py
SoftLayer/CLI/block/options.py
SoftLayer/CLI/block/order.py
SoftLayer/CLI/block/refresh.py
SoftLayer/CLI/block/set_note.py
softlayer-6.2.7.dist-info/licenses/LICENSE
softlayer-6.2.7.dist-info/METADATA
softlayer-6.2.7.dist-info/WHEEL
softlayer-6.2.7.dist-info/entry_points.txt
softlayer-6.2.7.dist-info/top_level.txt
softlayer-6.2.7.dist-info/RECORD
