Metadata-Version: 2.4
Name: SoftLayer
Version: 6.2.7
Summary: A library for SoftLayer's API
Home-page: https://github.com/SoftLayer/softlayer-python
Author: SoftLayer, Inc., an IBM Company
Author-email: SLDNDeveloperRelations@wwpdl.vnet.ibm.com
License: MIT
Keywords: softlayer,cloud,slcli,ibmcloud
Classifier: Environment :: Console
Classifier: Environment :: Web Environment
Classifier: Intended Audience :: Developers
Classifier: Intended Audience :: System Administrators
Classifier: License :: OSI Approved :: MIT License
Classifier: Operating System :: OS Independent
Classifier: Topic :: Software Development :: Libraries :: Python Modules
Classifier: Programming Language :: Python :: 3.7
Classifier: Programming Language :: Python :: 3.8
Classifier: Programming Language :: Python :: 3.9
Classifier: Programming Language :: Python :: 3.10
Classifier: Programming Language :: Python :: 3.11
Classifier: Programming Language :: Python :: 3.12
Classifier: Programming Language :: Python :: Implementation :: CPython
Classifier: Programming Language :: Python :: Implementation :: PyPy
Requires-Python: >=3.7
License-File: LICENSE
Requires-Dist: prettytable>=2.5.0
Requires-Dist: click>=8.0.4
Requires-Dist: requests>=2.32.2
Requires-Dist: prompt_toolkit>=2
Requires-Dist: pygments>=2.0.0
Requires-Dist: urllib3>=1.24
Requires-Dist: rich==14.0.0
Dynamic: author
Dynamic: author-email
Dynamic: classifier
Dynamic: description
Dynamic: description-content-type
Dynamic: home-page
Dynamic: keywords
Dynamic: license
Dynamic: license-file
Dynamic: requires-dist
Dynamic: requires-python
Dynamic: summary
